{
    "57a83260-98cb-b0a3-f978-e12b41b0060f": {
        "paletteKey": "FlexLayoutRow",
        "commentid": null,
        "designerReference": [
            {
                "_key": "componentLabel",
                "_value": "Row",
                "_type": "kv",
                "_attrDef": "p",
                "_useAsLabel": true
            },
            {
                "_key": "style",
                "_value": "",
                "_type": "kv",
                "_attrDef": "p"
            },
            {
                "_key": "class",
                "_value": "",
                "_type": "dav",
                "_attrDef": "p"
            },
            {
                "_key": "fxFlex",
                "_value": "100",
                "_type": "kv",
                "_attrDef": "p"
            },
            {
                "_key": "fxLayoutGap",
                "_value": "",
                "_type": "kv",
                "_attrDef": "p"
            },
            {
                "_key": "wrap",
                "_value": "wrap",
                "_type": "a",
                "_attrDef": "p"
            },
            {
                "_key": "layoutAlign",
                "_value": "start",
                "_type": "a",
                "_attrDef": "p"
            },
            {
                "_key": "pLayoutAlign",
                "_value": "center",
                "_type": "a",
                "_attrDef": "p"
            },
            {
                "_key": "[fxShow]",
                "_value": "true",
                "_type": "kv",
                "_attrDef": "p"
            }
        ],
        "03ba8ff0-6ba4-98f2-767e-6168dbe83b2c": {
            "paletteKey": "FlexLayoutCol",
            "parentEditorKey": "57a83260-98cb-b0a3-f978-e12b41b0060f",
            "commentid": null,
            "designerReference": [
                {
                    "_key": "componentLabel",
                    "_value": "Column",
                    "_type": "kv",
                    "_attrDef": "p",
                    "_useAsLabel": true
                },
                {
                    "_key": "style",
                    "_value": "",
                    "_type": "kv",
                    "_attrDef": "p"
                },
                {
                    "_key": "class",
                    "_value": "",
                    "_type": "dav",
                    "_attrDef": "p"
                },
                {
                    "_key": "fxFlex",
                    "_value": "100",
                    "_type": "kv",
                    "_attrDef": "p"
                },
                {
                    "_key": "fxLayoutGap",
                    "_value": "",
                    "_type": "kv",
                    "_attrDef": "p"
                },
                {
                    "_key": "wrap",
                    "_value": "wrap",
                    "_type": "a",
                    "_attrDef": "p"
                },
                {
                    "_key": "layoutAlign",
                    "_value": "start",
                    "_type": "a",
                    "_attrDef": "p"
                },
                {
                    "_key": "pLayoutAlign",
                    "_value": "center",
                    "_type": "a",
                    "_attrDef": "p"
                },
                {
                    "_key": "[fxShow]",
                    "_value": "true",
                    "_type": "kv",
                    "_attrDef": "p"
                }
            ],
            "12e524ca-13c8-ed72-0b19-78babcec4e06": {
                "paletteKey": "FlexLayoutRow",
                "parentEditorKey": "03ba8ff0-6ba4-98f2-767e-6168dbe83b2c",
                "commentid": null,
                "designerReference": [
                    {
                        "_key": "componentLabel",
                        "_value": "heading",
                        "_type": "kv",
                        "_attrDef": "p",
                        "_useAsLabel": true
                    },
                    {
                        "_key": "style",
                        "_value": "",
                        "_type": "kv",
                        "_attrDef": "p"
                    },
                    {
                        "_key": "class",
                        "_value": "",
                        "_type": "dav",
                        "_attrDef": "p"
                    },
                    {
                        "_key": "fxFlex",
                        "_value": "",
                        "_type": "kv",
                        "_attrDef": "p"
                    },
                    {
                        "_key": "fxLayoutGap",
                        "_value": "",
                        "_type": "kv",
                        "_attrDef": "p"
                    },
                    {
                        "_key": "wrap",
                        "_value": "wrap",
                        "_type": "a",
                        "_attrDef": "p"
                    },
                    {
                        "_key": "layoutAlign",
                        "_value": "start",
                        "_type": "a",
                        "_attrDef": "p"
                    },
                    {
                        "_key": "pLayoutAlign",
                        "_value": "stretch",
                        "_type": "a",
                        "_attrDef": "p"
                    },
                    {
                        "_key": "[fxShow]",
                        "_value": "true",
                        "_type": "kv",
                        "_attrDef": "p"
                    }
                ],
                "da37456d-18b1-2d77-125f-4d9221702d1c": {
                    "paletteKey": "Html5",
                    "parentEditorKey": "12e524ca-13c8-ed72-0b19-78babcec4e06",
                    "isAdvancedComponent": true,
                    "commentid": null,
                    "designerReference": [
                        {
                            "_key": "style",
                            "_value": "",
                            "_type": "kv",
                            "_attrDef": "p"
                        },
                        {
                            "_key": "class",
                            "_value": "",
                            "_type": "dav",
                            "_attrDef": "p"
                        },
                        {
                            "_key": "htmlElement",
                            "_value": "h2",
                            "_type": "dav",
                            "_attrDef": "p",
                            "_useAsLabel": true
                        },
                        {
                            "_key": "tagType",
                            "_value": "h2",
                            "_type": "a",
                            "_attrDef": "p",
                            "_visibility": false
                        },
                        {
                            "_key": "name",
                            "_value": "",
                            "_type": "kv",
                            "_attrDef": "p",
                            "_visibility": false
                        },
                        {
                            "_key": "sandbox",
                            "_value": "",
                            "_type": "kv",
                            "_attrDef": "p",
                            "_visibility": false
                        },
                        {
                            "_key": "src",
                            "_value": "",
                            "_type": "kv",
                            "_attrDef": "p",
                            "_visibility": false
                        },
                        {
                            "_key": "srcdoc",
                            "_value": "",
                            "_type": "kv",
                            "_attrDef": "p",
                            "_visibility": false
                        },
                        {
                            "_key": "width",
                            "_value": "",
                            "_type": "kv",
                            "_attrDef": "p",
                            "_visibility": false
                        },
                        {
                            "_key": "[autoplay]",
                            "_value": "",
                            "_type": "kv",
                            "_attrDef": "p",
                            "_visibility": false
                        },
                        {
                            "_key": "[loop]",
                            "_value": "",
                            "_type": "kv",
                            "_attrDef": "p",
                            "_visibility": false
                        },
                        {
                            "_key": "data",
                            "_value": "",
                            "_type": "kv",
                            "_attrDef": "p",
                            "_visibility": false
                        },
                        {
                            "_key": "audioSource",
                            "_value": [],
                            "_type": "a",
                            "_attrDef": "p",
                            "_visibility": false
                        },
                        {
                            "_key": "videoSource",
                            "_value": [],
                            "_type": "a",
                            "_attrDef": "p",
                            "_visibility": false
                        },
                        {
                            "_key": "audioDatasource",
                            "_value": "",
                            "_type": "a",
                            "_attrDef": "p",
                            "_visibility": false
                        },
                        {
                            "_key": "audioSrc",
                            "_value": "",
                            "_type": "a",
                            "_attrDef": "p",
                            "_visibility": false
                        },
                        {
                            "_key": "audioType",
                            "_value": "",
                            "_type": "a",
                            "_attrDef": "p",
                            "_visibility": false
                        },
                        {
                            "_key": "videoDatasource",
                            "_value": "",
                            "_type": "a",
                            "_attrDef": "p",
                            "_visibility": false
                        },
                        {
                            "_key": "videoSrc",
                            "_value": "",
                            "_type": "a",
                            "_attrDef": "p",
                            "_visibility": false
                        },
                        {
                            "_key": "videoType",
                            "_value": "",
                            "_type": "a",
                            "_attrDef": "p",
                            "_visibility": false
                        },
                        {
                            "_key": "(audioplay)",
                            "_value": "",
                            "_type": "a",
                            "_attrDef": "p",
                            "_visibility": false
                        },
                        {
                            "_key": "(videoplay)",
                            "_value": "",
                            "_type": "a",
                            "_attrDef": "p",
                            "_visibility": false
                        },
                        {
                            "_key": "(audiopause)",
                            "_value": "",
                            "_type": "kv",
                            "_attrDef": "p",
                            "_visibility": false
                        },
                        {
                            "_key": "(videopause)",
                            "_value": "",
                            "_type": "kv",
                            "_attrDef": "p",
                            "_visibility": false
                        },
                        {
                            "_key": "(audioended)",
                            "_value": "",
                            "_type": "kv",
                            "_attrDef": "p",
                            "_visibility": false
                        },
                        {
                            "_key": "(videoended)",
                            "_value": "",
                            "_type": "kv",
                            "_attrDef": "p",
                            "_visibility": false
                        }
                    ],
                    "d08fb6ab-7f8e-638c-a89d-7a6bae768559": {
                        "paletteKey": "html-editor",
                        "parentEditorKey": "da37456d-18b1-2d77-125f-4d9221702d1c",
                        "isAdvancedChildComponent": true,
                        "commentid": null,
                        "designerReference": [
                            {
                                "_key": "style",
                                "_value": "",
                                "_type": "kv",
                                "_attrDef": "p"
                            },
                            {
                                "_key": "class",
                                "_value": "",
                                "_type": "dav",
                                "_attrDef": "p"
                            },
                            {
                                "_key": "html",
                                "_value": "Welcome to NewsPortal Register",
                                "_type": "a",
                                "_attrDef": "p"
                            }
                        ]
                    }
                }
            },
            "154231d3-3f6c-09d0-eefa-5a46c66f2cba": {
                "paletteKey": "NG-Form",
                "parentEditorKey": "03ba8ff0-6ba4-98f2-767e-6168dbe83b2c",
                "commentid": null,
                "designerReference": [
                    {
                        "_key": "componentLabel",
                        "_value": "Form",
                        "_type": "kv",
                        "_attrDef": "p",
                        "_useAsLabel": true
                    },
                    {
                        "_key": "style",
                        "_value": "",
                        "_type": "kv",
                        "_attrDef": "p"
                    },
                    {
                        "_key": "class",
                        "_value": "",
                        "_type": "dav",
                        "_attrDef": "p"
                    },
                    {
                        "_key": "action",
                        "_value": "",
                        "_type": "kv",
                        "_attrDef": "p"
                    },
                    {
                        "_key": "method",
                        "_value": "",
                        "_type": "kv",
                        "_attrDef": "p"
                    },
                    {
                        "_key": "target",
                        "_value": "",
                        "_type": "kv",
                        "_attrDef": "p"
                    },
                    {
                        "_key": "(ngSubmit)",
                        "_value": "",
                        "_type": "kv",
                        "_attrDef": "p"
                    },
                    {
                        "_key": "(reset)",
                        "_value": "",
                        "_type": "kv",
                        "_attrDef": "p"
                    },
                    {
                        "_key": "#register",
                        "_value": "ngForm",
                        "_type": "kv",
                        "_attrDef": "c"
                    }
                ],
                "5c44f80c-699b-385e-50bd-f5896b18677c": {
                    "paletteKey": "FlexLayoutRow",
                    "parentEditorKey": "154231d3-3f6c-09d0-eefa-5a46c66f2cba",
                    "commentid": null,
                    "designerReference": [
                        {
                            "_key": "componentLabel",
                            "_value": "Row",
                            "_type": "kv",
                            "_attrDef": "p",
                            "_useAsLabel": true
                        },
                        {
                            "_key": "style",
                            "_value": "",
                            "_type": "kv",
                            "_attrDef": "p"
                        },
                        {
                            "_key": "class",
                            "_value": "",
                            "_type": "dav",
                            "_attrDef": "p"
                        },
                        {
                            "_key": "fxFlex",
                            "_value": "",
                            "_type": "kv",
                            "_attrDef": "p"
                        },
                        {
                            "_key": "fxLayoutGap",
                            "_value": "",
                            "_type": "kv",
                            "_attrDef": "p"
                        },
                        {
                            "_key": "wrap",
                            "_value": "wrap",
                            "_type": "a",
                            "_attrDef": "p"
                        },
                        {
                            "_key": "layoutAlign",
                            "_value": "start",
                            "_type": "a",
                            "_attrDef": "p"
                        },
                        {
                            "_key": "pLayoutAlign",
                            "_value": "stretch",
                            "_type": "a",
                            "_attrDef": "p"
                        },
                        {
                            "_key": "[fxShow]",
                            "_value": "true",
                            "_type": "kv",
                            "_attrDef": "p"
                        }
                    ],
                    "70f3a758-436e-b086-ddb1-9af61d84269c": {
                        "paletteKey": "NG-Input",
                        "parentEditorKey": "5c44f80c-699b-385e-50bd-f5896b18677c",
                        "isAdvancedComponent": true,
                        "commentid": null,
                        "designerReference": [
                            {
                                "_key": "style",
                                "_value": "",
                                "_type": "kv",
                                "_attrDef": "p"
                            },
                            {
                                "_key": "class",
                                "_value": "",
                                "_type": "dav",
                                "_attrDef": "p"
                            },
                            {
                                "_key": "placeholder",
                                "_value": "Enter Full name",
                                "_type": "kv",
                                "_attrDef": "p",
                                "_useAsLabel": true
                            },
                            {
                                "_key": "value",
                                "_value": "",
                                "_type": "kv",
                                "_attrDef": "p"
                            },
                            {
                                "_key": "[appearance]",
                                "_value": "'outline'",
                                "_type": "a",
                                "_attrDef": "p"
                            },
                            {
                                "_key": "[required]",
                                "_value": "true",
                                "_type": "kv",
                                "_attrDef": "p"
                            },
                            {
                                "_key": "[(ngModel)]",
                                "_value": "page.register.fullname",
                                "_type": "kv",
                                "_attrDef": "p"
                            },
                            {
                                "_key": "color",
                                "_value": "",
                                "_type": "kv",
                                "_attrDef": "p"
                            },
                            {
                                "_key": "name",
                                "_value": "fullname",
                                "_type": "kv",
                                "_attrDef": "p"
                            },
                            {
                                "_key": "type",
                                "_value": "",
                                "_type": "kv",
                                "_attrDef": "p"
                            },
                            {
                                "_key": "[formControl]",
                                "_value": "",
                                "_type": "kv",
                                "_attrDef": "p"
                            },
                            {
                                "_key": "readonly",
                                "_value": "",
                                "_type": "kv",
                                "_attrDef": "p"
                            },
                            {
                                "_key": "[disabled]",
                                "_value": "",
                                "_type": "kv",
                                "_attrDef": "p"
                            },
                            {
                                "_key": "id",
                                "_value": "",
                                "_type": "kv",
                                "_attrDef": "p"
                            },
                            {
                                "_key": "[floatLabel]",
                                "_value": "'auto'",
                                "_type": "kv",
                                "_attrDef": "p"
                            },
                            {
                                "_key": "[hideRequiredMarker]",
                                "_value": "false",
                                "_type": "kv",
                                "_attrDef": "p",
                                "_complexity": "advanced"
                            },
                            {
                                "_key": "matError",
                                "_value": [],
                                "_type": "a",
                                "_attrDef": "p",
                                "_visibility": true
                            },
                            {
                                "_key": "inputHint",
                                "_value": [],
                                "_type": "a",
                                "_attrDef": "p",
                                "_visibility": true
                            },
                            {
                                "_key": "Label",
                                "_value": "",
                                "_type": "a",
                                "_attrDef": "p",
                                "_visibility": true
                            },
                            {
                                "_key": "Suffix Icon",
                                "_value": "",
                                "_type": "a",
                                "_attrDef": "p",
                                "_visibility": true
                            },
                            {
                                "_key": "(suffixIconClick)",
                                "_value": "",
                                "_type": "a",
                                "_attrDef": "p",
                                "_visibility": true
                            },
                            {
                                "_key": "Prefix Icon",
                                "_value": "",
                                "_type": "a",
                                "_attrDef": "p",
                                "_visibility": true
                            },
                            {
                                "_key": "(prefixIconClick)",
                                "_value": "",
                                "_type": "a",
                                "_attrDef": "p",
                                "_visibility": true
                            },
                            {
                                "_key": "Prefix",
                                "_value": "",
                                "_type": "a",
                                "_attrDef": "p",
                                "_visibility": true
                            },
                            {
                                "_key": "Suffix",
                                "_value": "",
                                "_type": "a",
                                "_attrDef": "p",
                                "_visibility": true
                            },
                            {
                                "_key": "pattern",
                                "_value": "[a-z]{1,15}",
                                "_type": "kv",
                                "_attrDef": "c"
                            }
                        ]
                    }
                },
                "f367a055-2761-69d6-a161-6d88aa1cb2b5": {
                    "paletteKey": "FlexLayoutRow",
                    "parentEditorKey": "154231d3-3f6c-09d0-eefa-5a46c66f2cba",
                    "commentid": null,
                    "designerReference": [
                        {
                            "_key": "componentLabel",
                            "_value": "Row",
                            "_type": "kv",
                            "_attrDef": "p",
                            "_useAsLabel": true
                        },
                        {
                            "_key": "style",
                            "_value": "",
                            "_type": "kv",
                            "_attrDef": "p"
                        },
                        {
                            "_key": "class",
                            "_value": "",
                            "_type": "dav",
                            "_attrDef": "p"
                        },
                        {
                            "_key": "fxFlex",
                            "_value": "",
                            "_type": "kv",
                            "_attrDef": "p"
                        },
                        {
                            "_key": "fxLayoutGap",
                            "_value": "",
                            "_type": "kv",
                            "_attrDef": "p"
                        },
                        {
                            "_key": "wrap",
                            "_value": "wrap",
                            "_type": "a",
                            "_attrDef": "p"
                        },
                        {
                            "_key": "layoutAlign",
                            "_value": "start",
                            "_type": "a",
                            "_attrDef": "p"
                        },
                        {
                            "_key": "pLayoutAlign",
                            "_value": "stretch",
                            "_type": "a",
                            "_attrDef": "p"
                        },
                        {
                            "_key": "[fxShow]",
                            "_value": "true",
                            "_type": "kv",
                            "_attrDef": "p"
                        }
                    ],
                    "f7a76906-64d0-1937-4496-96851e686529": {
                        "paletteKey": "NG-Input",
                        "parentEditorKey": "f367a055-2761-69d6-a161-6d88aa1cb2b5",
                        "isAdvancedComponent": true,
                        "commentid": null,
                        "designerReference": [
                            {
                                "_key": "style",
                                "_value": "",
                                "_type": "kv",
                                "_attrDef": "p"
                            },
                            {
                                "_key": "class",
                                "_value": "",
                                "_type": "dav",
                                "_attrDef": "p"
                            },
                            {
                                "_key": "placeholder",
                                "_value": "Please enter Email",
                                "_type": "kv",
                                "_attrDef": "p",
                                "_useAsLabel": true
                            },
                            {
                                "_key": "value",
                                "_value": "",
                                "_type": "kv",
                                "_attrDef": "p"
                            },
                            {
                                "_key": "[appearance]",
                                "_value": "'outline'",
                                "_type": "a",
                                "_attrDef": "p"
                            },
                            {
                                "_key": "[required]",
                                "_value": "true",
                                "_type": "kv",
                                "_attrDef": "p"
                            },
                            {
                                "_key": "[(ngModel)]",
                                "_value": "page.register.email",
                                "_type": "kv",
                                "_attrDef": "p"
                            },
                            {
                                "_key": "color",
                                "_value": "",
                                "_type": "kv",
                                "_attrDef": "p"
                            },
                            {
                                "_key": "name",
                                "_value": "email",
                                "_type": "kv",
                                "_attrDef": "p"
                            },
                            {
                                "_key": "type",
                                "_value": "",
                                "_type": "kv",
                                "_attrDef": "p"
                            },
                            {
                                "_key": "[formControl]",
                                "_value": "",
                                "_type": "kv",
                                "_attrDef": "p"
                            },
                            {
                                "_key": "readonly",
                                "_value": "",
                                "_type": "kv",
                                "_attrDef": "p"
                            },
                            {
                                "_key": "[disabled]",
                                "_value": "",
                                "_type": "kv",
                                "_attrDef": "p"
                            },
                            {
                                "_key": "id",
                                "_value": "",
                                "_type": "kv",
                                "_attrDef": "p"
                            },
                            {
                                "_key": "[floatLabel]",
                                "_value": "'auto'",
                                "_type": "kv",
                                "_attrDef": "p"
                            },
                            {
                                "_key": "[hideRequiredMarker]",
                                "_value": "false",
                                "_type": "kv",
                                "_attrDef": "p",
                                "_complexity": "advanced"
                            },
                            {
                                "_key": "matError",
                                "_value": [],
                                "_type": "a",
                                "_attrDef": "p",
                                "_visibility": true
                            },
                            {
                                "_key": "inputHint",
                                "_value": [],
                                "_type": "a",
                                "_attrDef": "p",
                                "_visibility": true
                            },
                            {
                                "_key": "Label",
                                "_value": "",
                                "_type": "a",
                                "_attrDef": "p",
                                "_visibility": true
                            },
                            {
                                "_key": "Suffix Icon",
                                "_value": "",
                                "_type": "a",
                                "_attrDef": "p",
                                "_visibility": true
                            },
                            {
                                "_key": "(suffixIconClick)",
                                "_value": "",
                                "_type": "a",
                                "_attrDef": "p",
                                "_visibility": true
                            },
                            {
                                "_key": "Prefix Icon",
                                "_value": "",
                                "_type": "a",
                                "_attrDef": "p",
                                "_visibility": true
                            },
                            {
                                "_key": "(prefixIconClick)",
                                "_value": "",
                                "_type": "a",
                                "_attrDef": "p",
                                "_visibility": true
                            },
                            {
                                "_key": "Prefix",
                                "_value": "",
                                "_type": "a",
                                "_attrDef": "p",
                                "_visibility": true
                            },
                            {
                                "_key": "Suffix",
                                "_value": "",
                                "_type": "a",
                                "_attrDef": "p",
                                "_visibility": true
                            },
                            {
                                "_key": "pattern",
                                "_value": "[a-z0-9._%+-]+@[a-z0-9.-]+\\.[a-z]{2,4}$",
                                "_type": "kv",
                                "_attrDef": "c"
                            }
                        ]
                    }
                },
                "07422e85-15fb-3c3b-080e-e44da47bfaad": {
                    "paletteKey": "FlexLayoutRow",
                    "parentEditorKey": "154231d3-3f6c-09d0-eefa-5a46c66f2cba",
                    "commentid": null,
                    "designerReference": [
                        {
                            "_key": "componentLabel",
                            "_value": "Row",
                            "_type": "kv",
                            "_attrDef": "p",
                            "_useAsLabel": true
                        },
                        {
                            "_key": "style",
                            "_value": "",
                            "_type": "kv",
                            "_attrDef": "p"
                        },
                        {
                            "_key": "class",
                            "_value": "",
                            "_type": "dav",
                            "_attrDef": "p"
                        },
                        {
                            "_key": "fxFlex",
                            "_value": "",
                            "_type": "kv",
                            "_attrDef": "p"
                        },
                        {
                            "_key": "fxLayoutGap",
                            "_value": "",
                            "_type": "kv",
                            "_attrDef": "p"
                        },
                        {
                            "_key": "wrap",
                            "_value": "wrap",
                            "_type": "a",
                            "_attrDef": "p"
                        },
                        {
                            "_key": "layoutAlign",
                            "_value": "start",
                            "_type": "a",
                            "_attrDef": "p"
                        },
                        {
                            "_key": "pLayoutAlign",
                            "_value": "stretch",
                            "_type": "a",
                            "_attrDef": "p"
                        },
                        {
                            "_key": "[fxShow]",
                            "_value": "true",
                            "_type": "kv",
                            "_attrDef": "p"
                        }
                    ],
                    "202ec022-9609-d248-684c-c4316c01354e": {
                        "paletteKey": "NG-Input",
                        "parentEditorKey": "07422e85-15fb-3c3b-080e-e44da47bfaad",
                        "isAdvancedComponent": true,
                        "commentid": null,
                        "designerReference": [
                            {
                                "_key": "style",
                                "_value": "",
                                "_type": "kv",
                                "_attrDef": "p"
                            },
                            {
                                "_key": "class",
                                "_value": "",
                                "_type": "dav",
                                "_attrDef": "p"
                            },
                            {
                                "_key": "placeholder",
                                "_value": "Password",
                                "_type": "kv",
                                "_attrDef": "p",
                                "_useAsLabel": true
                            },
                            {
                                "_key": "value",
                                "_value": "",
                                "_type": "kv",
                                "_attrDef": "p"
                            },
                            {
                                "_key": "[appearance]",
                                "_value": "'outline'",
                                "_type": "a",
                                "_attrDef": "p"
                            },
                            {
                                "_key": "[required]",
                                "_value": "true",
                                "_type": "kv",
                                "_attrDef": "p"
                            },
                            {
                                "_key": "[(ngModel)]",
                                "_value": "page.register.password",
                                "_type": "kv",
                                "_attrDef": "p"
                            },
                            {
                                "_key": "color",
                                "_value": "",
                                "_type": "kv",
                                "_attrDef": "p"
                            },
                            {
                                "_key": "name",
                                "_value": "password",
                                "_type": "kv",
                                "_attrDef": "p"
                            },
                            {
                                "_key": "type",
                                "_value": "",
                                "_type": "kv",
                                "_attrDef": "p"
                            },
                            {
                                "_key": "[formControl]",
                                "_value": "",
                                "_type": "kv",
                                "_attrDef": "p"
                            },
                            {
                                "_key": "readonly",
                                "_value": "",
                                "_type": "kv",
                                "_attrDef": "p"
                            },
                            {
                                "_key": "[disabled]",
                                "_value": "",
                                "_type": "kv",
                                "_attrDef": "p"
                            },
                            {
                                "_key": "id",
                                "_value": "",
                                "_type": "kv",
                                "_attrDef": "p"
                            },
                            {
                                "_key": "[floatLabel]",
                                "_value": "'auto'",
                                "_type": "kv",
                                "_attrDef": "p"
                            },
                            {
                                "_key": "[hideRequiredMarker]",
                                "_value": "false",
                                "_type": "kv",
                                "_attrDef": "p",
                                "_complexity": "advanced"
                            },
                            {
                                "_key": "matError",
                                "_value": [],
                                "_type": "a",
                                "_attrDef": "p",
                                "_visibility": true
                            },
                            {
                                "_key": "inputHint",
                                "_value": [],
                                "_type": "a",
                                "_attrDef": "p",
                                "_visibility": true
                            },
                            {
                                "_key": "Label",
                                "_value": "",
                                "_type": "a",
                                "_attrDef": "p",
                                "_visibility": true
                            },
                            {
                                "_key": "Suffix Icon",
                                "_value": "",
                                "_type": "a",
                                "_attrDef": "p",
                                "_visibility": true
                            },
                            {
                                "_key": "(suffixIconClick)",
                                "_value": "",
                                "_type": "a",
                                "_attrDef": "p",
                                "_visibility": true
                            },
                            {
                                "_key": "Prefix Icon",
                                "_value": "",
                                "_type": "a",
                                "_attrDef": "p",
                                "_visibility": true
                            },
                            {
                                "_key": "(prefixIconClick)",
                                "_value": "",
                                "_type": "a",
                                "_attrDef": "p",
                                "_visibility": true
                            },
                            {
                                "_key": "Prefix",
                                "_value": "",
                                "_type": "a",
                                "_attrDef": "p",
                                "_visibility": true
                            },
                            {
                                "_key": "Suffix",
                                "_value": "",
                                "_type": "a",
                                "_attrDef": "p",
                                "_visibility": true
                            },
                            {
                                "_key": "pattern",
                                "_value": "(?=^.{8,}$)(?=.*\\d)(?=.*[!@#$%^&*]+)(?![.\\n])(?=.*[A-Z])(?=.*[a-z]).*$",
                                "_type": "kv",
                                "_attrDef": "c"
                            }
                        ]
                    }
                },
                "87e317b6-cbad-ebb4-2942-9afc561a9999": {
                    "paletteKey": "FlexLayoutRow",
                    "parentEditorKey": "154231d3-3f6c-09d0-eefa-5a46c66f2cba",
                    "commentid": null,
                    "designerReference": [
                        {
                            "_key": "componentLabel",
                            "_value": "Row",
                            "_type": "kv",
                            "_attrDef": "p",
                            "_useAsLabel": true
                        },
                        {
                            "_key": "style",
                            "_value": "",
                            "_type": "kv",
                            "_attrDef": "p"
                        },
                        {
                            "_key": "class",
                            "_value": "",
                            "_type": "dav",
                            "_attrDef": "p"
                        },
                        {
                            "_key": "fxFlex",
                            "_value": "",
                            "_type": "kv",
                            "_attrDef": "p"
                        },
                        {
                            "_key": "fxLayoutGap",
                            "_value": "",
                            "_type": "kv",
                            "_attrDef": "p"
                        },
                        {
                            "_key": "wrap",
                            "_value": "wrap",
                            "_type": "a",
                            "_attrDef": "p"
                        },
                        {
                            "_key": "layoutAlign",
                            "_value": "start",
                            "_type": "a",
                            "_attrDef": "p"
                        },
                        {
                            "_key": "pLayoutAlign",
                            "_value": "stretch",
                            "_type": "a",
                            "_attrDef": "p"
                        },
                        {
                            "_key": "[fxShow]",
                            "_value": "true",
                            "_type": "kv",
                            "_attrDef": "p"
                        }
                    ],
                    "17e06f79-ab9e-5a56-6544-6b9c385b4779": {
                        "paletteKey": "NG-button",
                        "parentEditorKey": "87e317b6-cbad-ebb4-2942-9afc561a9999",
                        "commentid": null,
                        "designerReference": [
                            {
                                "_key": "style",
                                "_value": "",
                                "_type": "kv",
                                "_attrDef": "p"
                            },
                            {
                                "_key": "class",
                                "_value": "",
                                "_type": "dav",
                                "_attrDef": "p"
                            },
                            {
                                "_key": "buttonname",
                                "_value": "Register",
                                "_type": "a",
                                "_attrDef": "p",
                                "_useAsLabel": true
                            },
                            {
                                "_key": "color",
                                "_value": "",
                                "_type": "kv",
                                "_attrDef": "p"
                            },
                            {
                                "_key": "(click)",
                                "_value": "registerSubmit(register.value)",
                                "_type": "kv",
                                "_attrDef": "p",
                                "objValue": {
                                    "nodeID": "sd_Bddc5vWDnF9hFPgY",
                                    "functionName": "registerSubmit",
                                    "activeTree": "pages",
                                    "z": "sd_yHKC7a7Zwo4tLWnD",
                                    "input": [
                                        "register.value"
                                    ]
                                }
                            },
                            {
                                "_key": "[disabled]",
                                "_value": "register.invalid",
                                "_type": "kv",
                                "_attrDef": "p",
                                "_customAttributeFlag": "customInput"
                            },
                            {
                                "_key": "[disableRipple]",
                                "_value": "",
                                "_type": "kv",
                                "_attrDef": "p"
                            },
                            {
                                "_key": "type",
                                "_value": "",
                                "_type": "kv",
                                "_attrDef": "p"
                            },
                            {
                                "_key": "routerLink",
                                "_value": "",
                                "_type": "kv",
                                "_attrDef": "p"
                            }
                        ]
                    }
                }
            },
            "1360b14e-4b93-6806-a061-c31c63b441fc": {
                "paletteKey": "FlexLayoutRow",
                "parentEditorKey": "03ba8ff0-6ba4-98f2-767e-6168dbe83b2c",
                "commentid": null,
                "designerReference": [
                    {
                        "_key": "componentLabel",
                        "_value": "Row",
                        "_type": "kv",
                        "_attrDef": "p",
                        "_useAsLabel": true
                    },
                    {
                        "_key": "style",
                        "_value": "",
                        "_type": "kv",
                        "_attrDef": "p"
                    },
                    {
                        "_key": "class",
                        "_value": [
                            "margintop10px"
                        ],
                        "_type": "dav",
                        "_attrDef": "p"
                    },
                    {
                        "_key": "fxFlex",
                        "_value": "",
                        "_type": "kv",
                        "_attrDef": "p"
                    },
                    {
                        "_key": "fxLayoutGap",
                        "_value": "",
                        "_type": "kv",
                        "_attrDef": "p"
                    },
                    {
                        "_key": "wrap",
                        "_value": "wrap",
                        "_type": "a",
                        "_attrDef": "p"
                    },
                    {
                        "_key": "layoutAlign",
                        "_value": "start",
                        "_type": "a",
                        "_attrDef": "p"
                    },
                    {
                        "_key": "pLayoutAlign",
                        "_value": "stretch",
                        "_type": "a",
                        "_attrDef": "p"
                    },
                    {
                        "_key": "[fxShow]",
                        "_value": "true",
                        "_type": "kv",
                        "_attrDef": "p"
                    }
                ],
                "9c987d0a-8986-422d-fccd-79322f3e503d": {
                    "paletteKey": "Html5",
                    "parentEditorKey": "1360b14e-4b93-6806-a061-c31c63b441fc",
                    "isAdvancedComponent": true,
                    "commentid": null,
                    "designerReference": [
                        {
                            "_key": "style",
                            "_value": "",
                            "_type": "kv",
                            "_attrDef": "p"
                        },
                        {
                            "_key": "class",
                            "_value": "",
                            "_type": "dav",
                            "_attrDef": "p"
                        },
                        {
                            "_key": "htmlElement",
                            "_value": "h4",
                            "_type": "dav",
                            "_attrDef": "p",
                            "_useAsLabel": true
                        },
                        {
                            "_key": "tagType",
                            "_value": "h4",
                            "_type": "a",
                            "_attrDef": "p",
                            "_visibility": false
                        },
                        {
                            "_key": "name",
                            "_value": "",
                            "_type": "kv",
                            "_attrDef": "p",
                            "_visibility": false
                        },
                        {
                            "_key": "sandbox",
                            "_value": "",
                            "_type": "kv",
                            "_attrDef": "p",
                            "_visibility": false
                        },
                        {
                            "_key": "src",
                            "_value": "",
                            "_type": "kv",
                            "_attrDef": "p",
                            "_visibility": false
                        },
                        {
                            "_key": "srcdoc",
                            "_value": "",
                            "_type": "kv",
                            "_attrDef": "p",
                            "_visibility": false
                        },
                        {
                            "_key": "width",
                            "_value": "",
                            "_type": "kv",
                            "_attrDef": "p",
                            "_visibility": false
                        },
                        {
                            "_key": "[autoplay]",
                            "_value": "",
                            "_type": "kv",
                            "_attrDef": "p",
                            "_visibility": false
                        },
                        {
                            "_key": "[loop]",
                            "_value": "",
                            "_type": "kv",
                            "_attrDef": "p",
                            "_visibility": false
                        },
                        {
                            "_key": "data",
                            "_value": "",
                            "_type": "kv",
                            "_attrDef": "p",
                            "_visibility": false
                        },
                        {
                            "_key": "audioSource",
                            "_value": [],
                            "_type": "a",
                            "_attrDef": "p",
                            "_visibility": false
                        },
                        {
                            "_key": "videoSource",
                            "_value": [],
                            "_type": "a",
                            "_attrDef": "p",
                            "_visibility": false
                        },
                        {
                            "_key": "audioDatasource",
                            "_value": "",
                            "_type": "a",
                            "_attrDef": "p",
                            "_visibility": false
                        },
                        {
                            "_key": "audioSrc",
                            "_value": "",
                            "_type": "a",
                            "_attrDef": "p",
                            "_visibility": false
                        },
                        {
                            "_key": "audioType",
                            "_value": "",
                            "_type": "a",
                            "_attrDef": "p",
                            "_visibility": false
                        },
                        {
                            "_key": "videoDatasource",
                            "_value": "",
                            "_type": "a",
                            "_attrDef": "p",
                            "_visibility": false
                        },
                        {
                            "_key": "videoSrc",
                            "_value": "",
                            "_type": "a",
                            "_attrDef": "p",
                            "_visibility": false
                        },
                        {
                            "_key": "videoType",
                            "_value": "",
                            "_type": "a",
                            "_attrDef": "p",
                            "_visibility": false
                        },
                        {
                            "_key": "(audioplay)",
                            "_value": "",
                            "_type": "a",
                            "_attrDef": "p",
                            "_visibility": false
                        },
                        {
                            "_key": "(videoplay)",
                            "_value": "",
                            "_type": "a",
                            "_attrDef": "p",
                            "_visibility": false
                        },
                        {
                            "_key": "(audiopause)",
                            "_value": "",
                            "_type": "kv",
                            "_attrDef": "p",
                            "_visibility": false
                        },
                        {
                            "_key": "(videopause)",
                            "_value": "",
                            "_type": "kv",
                            "_attrDef": "p",
                            "_visibility": false
                        },
                        {
                            "_key": "(audioended)",
                            "_value": "",
                            "_type": "kv",
                            "_attrDef": "p",
                            "_visibility": false
                        },
                        {
                            "_key": "(videoended)",
                            "_value": "",
                            "_type": "kv",
                            "_attrDef": "p",
                            "_visibility": false
                        }
                    ],
                    "b98ef0aa-08a5-5e3b-e0c8-137e72b5091a": {
                        "paletteKey": "html-editor",
                        "parentEditorKey": "9c987d0a-8986-422d-fccd-79322f3e503d",
                        "isAdvancedChildComponent": true,
                        "commentid": null,
                        "designerReference": [
                            {
                                "_key": "style",
                                "_value": "",
                                "_type": "kv",
                                "_attrDef": "p"
                            },
                            {
                                "_key": "class",
                                "_value": "",
                                "_type": "dav",
                                "_attrDef": "p"
                            },
                            {
                                "_key": "html",
                                "_value": "<a routerLink=\"../login\">Already have an account?</a>",
                                "_type": "a",
                                "_attrDef": "p"
                            }
                        ]
                    }
                }
            }
        }
    }
}
